namekox_prometheus/__init__.py
namekox_prometheus/constants.py
namekox_prometheus/cli/__init__.py
namekox_prometheus/cli/subctx/__init__.py
namekox_prometheus/cli/subctx/prometheus.py
namekox_prometheus/core/__init__.py
namekox_prometheus/core/gateway.py
namekox_prometheus/core/proxy.py
namekox_prometheus/core/dependencies/__init__.py
namekox_prometheus-0.0.4.dist-info/METADATA
namekox_prometheus-0.0.4.dist-info/WHEEL
namekox_prometheus-0.0.4.dist-info/top_level.txt
namekox_prometheus-0.0.4.dist-info/zip-safe
namekox_prometheus-0.0.4.dist-info/RECORD
